Topsis_Kunal_102216002/__init__.py
Topsis_Kunal_102216002/topsis.py
Topsis_Kunal_102216002-4.0.1.dist-info/LICENSE
Topsis_Kunal_102216002-4.0.1.dist-info/METADATA
Topsis_Kunal_102216002-4.0.1.dist-info/WHEEL
Topsis_Kunal_102216002-4.0.1.dist-info/entry_points.txt
Topsis_Kunal_102216002-4.0.1.dist-info/top_level.txt
Topsis_Kunal_102216002-4.0.1.dist-info/RECORD
