Metadata-Version: 2.1
Name: Topsis-Kunal-102216002
Version: 4.0.1
Summary: A Python package to perform TOPSIS analysis
Home-page: https://github.com/Kunal-code-u/Topsis-Kunal-102216002
Author: Kunal
Author-email: kbhalla600@gmail.com
Classifier: Programming Language :: Python :: 3
Classifier: License :: OSI Approved :: MIT License
Classifier: Operating System :: OS Independent
Requires-Python: >=3.6
License-File: LICENSE
Requires-Dist: pandas
Requires-Dist: numpy
